LICENSE
README.md
setup.py
blob_masks/__init__.py
blob_masks/blob_masks.py
blob_masks.egg-info/PKG-INFO
blob_masks.egg-info/SOURCES.txt
blob_masks.egg-info/dependency_links.txt
blob_masks.egg-info/requires.txt
blob_masks.egg-info/top_level.txt