Metadata-Version: 2.1
Name: blob-masks
Version: 0.1.3
Summary: Generate white potato shaped blobs on black backgrounds
Home-page: https://github.com/SINTEF/python-blob-masks
Author: Antoine Pultier
Author-email: antoine.pultier@sintef.no
Classifier: Development Status :: 4 - Beta
Classifier: Intended Audience :: Developers
Classifier: License :: Public Domain
Classifier: Programming Language :: Python :: 3
Classifier: Programming Language :: Python :: 3.6
Classifier: Programming Language :: Python :: 3.7
Classifier: Programming Language :: Python :: 3.8
Classifier: Programming Language :: Python :: 3.9
Classifier: Programming Language :: Python :: 3.10
License-File: LICENSE
